{
    "prepare_queue": {
        "installed": [],
        "uninstalled": []
    },
    "config_munge": {
        "files": {
            "config.xml": {
                "parents": {
                    "/*": [
                        {
                            "xml": "<feature name=\"Keyboard\"><param name=\"ios-package\" onload=\"true\" value=\"IonicKeyboard\" /></feature>",
                            "count": 1
                        },
                        {
                            "xml": "<feature name=\"Console\"><param name=\"ios-package\" value=\"CDVLogger\" /></feature>",
                            "count": 1
                        },
                        {
                            "xml": "<feature name=\"Device\"><param name=\"ios-package\" value=\"CDVDevice\" /></feature>",
                            "count": 1
                        },
                        {
                            "xml": "<feature name=\"Contacts\"><param name=\"ios-package\" value=\"CDVContacts\" /></feature>",
                            "count": 1
                        }
                    ]
                }
            },
            "framework": {
                "parents": {
                    "AddressBook.framework": [
                        {
                            "xml": "true",
                            "count": 1
                        }
                    ],
                    "AddressBookUI.framework": [
                        {
                            "xml": "true",
                            "count": 1
                        }
                    ],
                    "CoreGraphics.framework": [
                        {
                            "xml": "false",
                            "count": 1
                        }
                    ]
                }
            }
        }
    },
    "installed_plugins": {
        "com.ionic.keyboard": {
            "PACKAGE_NAME": "com.ionicframework.onthegomobile448258"
        },
        "org.apache.cordova.console": {
            "PACKAGE_NAME": "com.ionicframework.onthegomobile448258"
        },
        "org.apache.cordova.device": {
            "PACKAGE_NAME": "com.ionicframework.onthegomobile448258"
        },
        "org.apache.cordova.contacts": {
            "PACKAGE_NAME": "com.zend.onthegomobile"
        }
    },
    "dependent_plugins": {}
}